MANIFEST.in
setup.cfg
setup.py
versioneer.py
mmd/__init__.py
mmd/_mmd.c
mmd/_version.py
mmd/mmd.py
mmd/utils.py
mmd.egg-info/PKG-INFO
mmd.egg-info/SOURCES.txt
mmd.egg-info/dependency_links.txt
mmd.egg-info/not-zip-safe
mmd.egg-info/requires.txt
mmd.egg-info/top_level.txt