Metadata-Version: 1.0
Name: mmd
Version: 0.2.2
Summary: Some utilities for dealing with the Maximum Mean Discrepancy (MMD) and related tools
Home-page: https://github.com/dougalsutherland/mmd/
Author: Dougal J. Sutherland
Author-email: dougal@gmail.com
License: UNKNOWN
Platform: UNKNOWN
